kafkaboost/__init__.py
kafkaboost/aws_config.py
kafkaboost/aws_config_template.json
kafkaboost/consumer.py
kafkaboost/kafka_utils.py
kafkaboost/priority_consumer_manager.py
kafkaboost/producer.py
kafkaboost/s3_config_local.json
kafkaboost/s3_config_manager.py
kafkaboost/__pycache__/aws_config.cpython-311.pyc
kafkaboost/__pycache__/config_manager.cpython-311.pyc
kafkaboost/__pycache__/consumer.cpython-311.pyc
kafkaboost/__pycache__/kafka_utils.cpython-311.pyc
kafkaboost/__pycache__/producer.cpython-311.pyc
kafkaboost/__pycache__/s3_config_manager.cpython-311.pyc
kafkaboost/tests/debug_s3_test.py
kafkaboost/tests/s3_config_local.json
kafkaboost/tests/sample_config.json
kafkaboost/tests/simple_s3_test.py
kafkaboost/tests/test_background_polling.py
kafkaboost/tests/test_config.json
kafkaboost/tests/test_kafka_utils.py
kafkaboost/tests/test_kafkaboost.py
kafkaboost/tests/test_priority_boost_kafka.py
kafkaboost/tests/__pycache__/test_kafka_utils.cpython-311-pytest-7.4.0.pyc
kafkaboost/tests/__pycache__/test_kafkaboost.cpython-311-pytest-7.4.0.pyc
kafkaboost/tests/__pycache__/test_kafkaboost.cpython-311.pyc
kafkaboost-0.2.0.dist-info/METADATA
kafkaboost-0.2.0.dist-info/WHEEL
kafkaboost-0.2.0.dist-info/entry_points.txt
kafkaboost-0.2.0.dist-info/top_level.txt
kafkaboost-0.2.0.dist-info/RECORD
