Metadata-Version: 2.4
Name: kafkaboost
Version: 0.2.0
Summary: Enhanced Apache Kafka library with priority-based message processing
Home-page: https://github.com/your-org/kafkaboost
Author: KafkaBoost Team
Author-email: KafkaBoost Team <support@kafkaboost.com>
Maintainer-email: KafkaBoost Team <support@kafkaboost.com>
License: MIT
Project-URL: Homepage, https://github.com/your-org/kafkaboost
Project-URL: Documentation, https://kafkaboost.readthedocs.io/
Project-URL: Repository, https://github.com/your-org/kafkaboost
Project-URL: Bug Tracker, https://github.com/your-org/kafkaboost/issues
Keywords: kafka,priority,messaging,distributed,streaming,async
Classifier: Development Status :: 4 - Beta
Classifier: Intended Audience :: Developers
Classifier: License :: OSI Approved :: MIT License
Classifier: Operating System :: OS Independent
Classifier: Programming Language :: Python :: 3
Classifier: Programming Language :: Python :: 3.7
Classifier: Programming Language :: Python :: 3.8
Classifier: Programming Language :: Python :: 3.9
Classifier: Programming Language :: Python :: 3.10
Classifier: Programming Language :: Python :: 3.11
Classifier: Topic :: Software Development :: Libraries :: Python Modules
Classifier: Topic :: System :: Distributed Computing
Classifier: Topic :: System :: Networking
Requires-Python: >=3.7
Requires-Dist: kafka-python>=2.2.15
Requires-Dist: boto3>=1.40.25
Requires-Dist: botocore>=1.40.25
Requires-Dist: requests>=2.25.0
Provides-Extra: dev
Requires-Dist: pytest>=6.0; extra == "dev"
Requires-Dist: pytest-asyncio>=0.18.0; extra == "dev"
Requires-Dist: black>=22.0; extra == "dev"
Requires-Dist: flake8>=4.0; extra == "dev"
Requires-Dist: mypy>=0.950; extra == "dev"
Provides-Extra: test
Requires-Dist: pytest>=6.0; extra == "test"
Requires-Dist: pytest-asyncio>=0.18.0; extra == "test"
Requires-Dist: pytest-cov>=3.0; extra == "test"
Dynamic: author
Dynamic: home-page
Dynamic: requires-python
